setup.cfg
setup.py
ph5/__init__.py
ph5.egg-info/PKG-INFO
ph5.egg-info/SOURCES.txt
ph5.egg-info/dependency_links.txt
ph5.egg-info/entry_points.txt
ph5.egg-info/top_level.txt
ph5/clients/__init__.py
ph5/clients/ph5toevt.py
ph5/clients/ph5toexml.py
ph5/clients/ph5toms.py
ph5/clients/ph5torec.py
ph5/clients/ph5tostationxml.py
ph5/clients/ph5view/__init__.py
ph5/clients/ph5view/ph5_viewer.py
ph5/clients/ph5view/ph5_viewer_reader.py
ph5/core/__init__.py
ph5/core/columns.py
ph5/core/cs2cs.py
ph5/core/decimate.py
ph5/core/ebcdic.py
ph5/core/experiment.py
ph5/core/ibmfloat.py
ph5/core/kef.py
ph5/core/kefutility.py
ph5/core/kefx.py
ph5/core/mplturkey.py
ph5/core/ph5api.py
ph5/core/ph5utils.py
ph5/core/pmonitor.py
ph5/core/pn125.py
ph5/core/pn130.py
ph5/core/rt_130_h.py
ph5/core/sac_h.py
ph5/core/sacfactory.py
ph5/core/sacreader.py
ph5/core/segd_h.py
ph5/core/segdreader.py
ph5/core/segy_h.py
ph5/core/segyfactory.py
ph5/core/segyreader.py
ph5/core/sfactory.py
ph5/core/timedoy.py
ph5/utilities/125a2ph5.py
ph5/utilities/1302ph5.py
ph5/utilities/__init__.py
ph5/utilities/changes.py
ph5/utilities/cross_check_event_array_data.py
ph5/utilities/dumpfair.py
ph5/utilities/dumpsac.py
ph5/utilities/dumpsgy.py
ph5/utilities/fix_3chan_texan.py
ph5/utilities/fix_num_samples.py
ph5/utilities/geod2kef.py
ph5/utilities/grao2ph5.py
ph5/utilities/index_offset_t.py
ph5/utilities/initialize_ph5.py
ph5/utilities/kef2kml.py
ph5/utilities/kef2ph5.py
ph5/utilities/kefedit.py
ph5/utilities/load_das_t.py
ph5/utilities/meta_data_gen.py
ph5/utilities/noven.py
ph5/utilities/novenkef.py
ph5/utilities/novenqc.py
ph5/utilities/novitiate.py
ph5/utilities/nuke_table.py
ph5/utilities/pforma_io.py
ph5/utilities/pformacl.py
ph5/utilities/pformagui.py
ph5/utilities/ph5_merge_helper.py
ph5/utilities/ph5_total.py
ph5/utilities/recreate_external_references.py
ph5/utilities/report2ph5.py
ph5/utilities/report_gen.py
ph5/utilities/seg2toph5.py
ph5/utilities/segd2ph5.py
ph5/utilities/segy2ph5.py
ph5/utilities/set_deploy_pickup_times.py
ph5/utilities/set_n_i_response.py
ph5/utilities/sort_array_t.py
ph5/utilities/sort_kef_gen.py
ph5/utilities/tabletokef.py
